{
    "wardrobe1": {
        "root": {
            "text": "這裡沒有什麼有用的東西。"
        }
    },

    "wardrobe2": {
        "root": {
            "text": "我冇嘢需要。"
        }
    },


    "bed": {
        "root": {
                "text": "嗯…我現在應該去睡覺嗎？"
            },
            "choices": [
                {
                    "text": "係"
                },
                {
                    "text": "唔係"
                }
            ],
        "noPhone": [
            {
                "text": "但係我而家用唔到電話嘅鬧鐘。"
            },
            {
                "text": "嗯，我會用返部舊電話，但係冇SIM卡，淨係可以當鬧鐘"
            },
            {
                "text": "好啦，校咗鬧鐘，準備瞓覺。"
            }
        ]
    },

    "phone": {
        "root": {
            "text": "我睇到你刪除了你的帖子，上面有你的電話號碼，不過唔使擔心，我截咗圖啦，我可以再上傳一次哈哈哈"
        }
    }
    
}